{ 
    "name": "Sanjay Goraniya",
    "title": "Sanjay Goraniya | Front End Software Engineer",
    "description": "Design-minded front-end software engineer focused on building beautiful interfaces and experiences",
    "url": "https://sanjaygoraniya.com/",
    "baseurl": "sanjaygoraniya.github.io",
    "email": "sanjayrgoraniya@gmail.com",
    "cover": "/img/og.png",
    "logo": "/img/logo/logo1.png",
    "data": {
        "resume": "/resume.pdf",
        "skills": {
            "languages": ["JavaScript (ES6+)", "TypeScript", "PHP", "HTML", "CSS/Sass", "Python", "GraphQL"],
            "frameworks": ["Node.js", "React", "Express", "jQuery", "Nunjucks", "Vue", "Wordpress", "Socket.IO"],
            "tools": ["Bash", "Git & Github", "Docker", "Chrome DevTools", "Postman", "MongoDB", "Passport.js","MySQL", "AWS", "Reaction Commerce"],
            "design": ["Sketch", "InDesign", "InVision", "Prototyping", "User Testing"]
        },
        "experience": [{
            "company": "Techitree",
            "url": "https://www.techitree.com",
            "time": "October 2019 - Present",
            "position": "MEAN Developer"
        },{
            "company": "AIS Technolabs",
            "url": "https://www.aistechnolabs.com",
            "time": "April 2019 - October 2019",
            "position": "NodeJS Developer"
        },{
            "company": "IANT (Institute Of Advance Network Technology)",
            "url": "https://www.iantindia.com",
            "time": "June 2016 - July 2017",
            "position": "PHP Developer"
        }],
        "otherProjects": [{
            "name": "Personal Website V1",
            "description": "My first portfolio website I designed and built in 2020. I learned quite a bit about HTML, CSS, and SEO. Since then, I think my web development and design skills have improved immensely.",
            "used": ["Node", "Express", "Nunjucks","JavaScript", "jQuery", "HTML", "CSS"],
            "links" : [
                {
                    "title": "Website",
                    "url": "https://sanjaygoraniya.com"
                },
                {
                    "title": "GitHub",
                    "url": "https://github.com/sanjaygoraniya"
                }
            ]
        },{
            "name": "WhatsApp Clone - Design",
            "description": "Small CSS design project created during my free time.",
            "used": ["JavaScript", "HTML", "CSS"],
            "links" : [
                {
                    "title": "Website",
                    "url": "https://github.com/sanjaygoraniya"
                },
                {
                    "title": "GitHub",
                    "url": "https://github.com/sanjaygoraniya"
                }
            ]
        },{
            "name": "Blog management",
            "description": "A complete solution to share knowledge, write blog, manage blog and profile.",
            "used": ["Node", "JavaScript", "GraphQL", "MongoDB", "React"],
            "links" : [
                {
                    "title": "Website",
                    "url": "https://www.careerchips.com"
                },
                {
                    "title": "GitHub",
                    "url": "https://github.com/sanjaygoraniya"
                }
            ]
        },{
            "name": "Ecommerce–LuxyList",
            "description": "LuxyList is e-commerce website like online store",
            "used": ["RC(Reaction-Commerce)", "Node", "JavaScript", "HTML","CSS", "GraphQL", "MongoDB", "Next"],
            "links" : [
                {
                    "title": "Website",
                    "url": "https://github.com/sanjaygoraniya"
                },
                {
                    "title": "GitHub",
                    "url": "https://github.com/sanjaygoraniya"
                }
            ]
        },{
            "name": "CareerChips",
            "description": "This web application is using for hire IT resource. CareerChips doesn’t ask for any login and that benefits individuals to refer their friends.",
            "used": [ "Node", "GraphQL", "JavaScript", "MongoDB", "React"],
            "links" : [
                {
                    "title": "Website",
                    "url": "https://www.careerchips.com"
                },
                {
                    "title": "GitHub",
                    "url": "https://github.com/sanjaygoraniya"
                }
            ]
        },{
            "name": "CSGOClub",
            "description": "CSGOClub is a web application for multiple games. In this project more then 10(ten) games are developed.",
            "used": ["Node", "Express", "MySQL", "JavaScript", "jQuery", "HTML", "CSS"],
            "links" : [
                {
                    "title": "Website",
                    "url": "https://github.com/sanjaygoraniya"
                },
                {
                    "title": "GitHub",
                    "url": "https://github.com/sanjaygoraniya"
                }
            ]
        }],
        "social": [
            { 
                "title": "Email",
                "url": "mailto:sanjayrgoraniya@gmail.com"
            },
            { 
                "title": "Instagram",
                "url": "https://www.instagram.com/sanjayrgoraniya"
            },
            { 
                "title": "GitHub",
                "url": "https://github.com/sanjaygoraniya"
            },
            { 
                "title": "LinkedIn",
                "url": "https://www.linkedin.com/in/sanjaygoraniya"
            }
        ]
    }
}
